<?xml version="1.0" encoding="UTF-8" standalone="no"?>
<annotation>
    <folder>Images</folder>
    <filename>img_15805.jpg</filename>
    <source>
        <database>Unknown</database>
    </source>
    <size>
        <width>523</width>
        <height>815</height>
        <depth>3</depth>
    </size>
    <segmented>0</segmented>
    <object>
        <name>酒瓶</name>
        <pose>Unspecified</pose>
        <truncated>0</truncated>
        <difficult>0</difficult>
        <occluded>0</occluded>
        <polygon>
            <x1>193</x1>
            <y1>48</y1>
            <x2>217</x2>
            <y2>72</y2>
            <x3>182</x3>
            <y3>156</y3>
            <x4>204</x4>
            <y4>174</y4>
            <x5>195</x5>
            <y5>203</y5>
            <x6>145</x6>
            <y6>225</y6>
            <x7>100</x7>
            <y7>261</y7>
            <x8>74</x8>
            <y8>314</y8>
            <x9>81</x9>
            <y9>449</y9>
            <x10>154</x10>
            <y10>705</y10>
            <x11>207</x11>
            <y11>737</y11>
            <x12>264</x12>
            <y12>754</y12>
            <x13>318</x13>
            <y13>745</y13>
            <x14>358</x14>
            <y14>723</y14>
            <x15>402</x15>
            <y15>666</y15>
            <x16>451</x16>
            <y16>449</y16>
            <x17>460</x17>
            <y17>363</y17>
            <x18>439</x18>
            <y18>260</y18>
            <x19>393</x19>
            <y19>230</y19>
            <x20>348</x20>
            <y20>205</y20>
            <x21>324</x21>
            <y21>180</y21>
            <x22>348</x22>
            <y22>156</y22>
            <x23>319</x23>
            <y23>79</y23>
            <x24>346</x24>
            <y24>38</y24>
            <x25>323</x25>
            <y25>16</y25>
            <x26>264</x26>
            <y26>9</y26>
            <x27>202</x27>
            <y27>17</y27>
            <x28>193</x28>
            <y28>48</y28>
        </polygon>
    </object>
</annotation>
