<?xml version="1.0" encoding="UTF-8" standalone="no"?>
<annotation>
    <folder>Images</folder>
    <filename>img_10069.jpg</filename>
    <source>
        <database>Unknown</database>
    </source>
    <size>
        <width>511</width>
        <height>549</height>
        <depth>3</depth>
    </size>
    <segmented>0</segmented>
    <object>
        <name>插头电线</name>
        <pose>Unspecified</pose>
        <truncated>0</truncated>
        <difficult>0</difficult>
        <occluded>0</occluded>
        <polygon>
            <x1>246</x1>
            <y1>46</y1>
            <x2>251</x2>
            <y2>117</y2>
            <x3>289</x3>
            <y3>144</y3>
            <x4>408</x4>
            <y4>130</y4>
            <x5>416</x5>
            <y5>147</y5>
            <x6>469</x6>
            <y6>143</y6>
            <x7>470</x7>
            <y7>122</y7>
            <x8>502</x8>
            <y8>122</y8>
            <x9>509</x9>
            <y9>87</y9>
            <x10>489</x10>
            <y10>84</y10>
            <x11>493</x11>
            <y11>30</y11>
            <x12>246</x12>
            <y12>46</y12>
        </polygon>
    </object>
    <object>
        <name>插头电线</name>
        <pose>Unspecified</pose>
        <truncated>0</truncated>
        <difficult>0</difficult>
        <occluded>0</occluded>
        <polygon>
            <x1>22</x1>
            <y1>337</y1>
            <x2>10</x2>
            <y2>370</y2>
            <x3>22</x3>
            <y3>406</y3>
            <x4>50</x4>
            <y4>421</y4>
            <x5>79</x5>
            <y5>433</y5>
            <x6>85</x6>
            <y6>419</y6>
            <x7>256</x7>
            <y7>405</y7>
            <x8>486</x8>
            <y8>401</y8>
            <x9>473</x9>
            <y9>424</y9>
            <x10>506</x10>
            <y10>431</y10>
            <x11>502</x11>
            <y11>455</y11>
            <x12>417</x12>
            <y12>472</y12>
            <x13>363</x13>
            <y13>472</y13>
            <x14>321</x14>
            <y14>488</y14>
            <x15>280</x15>
            <y15>485</y15>
            <x16>221</x16>
            <y16>478</y16>
            <x17>159</x17>
            <y17>476</y17>
            <x18>67</x18>
            <y18>471</y18>
            <x19>16</x19>
            <y19>461</y19>
            <x20>0</x20>
            <y20>423</y20>
            <x21>0</x21>
            <y21>361</y21>
            <x22>5</x22>
            <y22>323</y22>
            <x23>22</x23>
            <y23>337</y23>
        </polygon>
    </object>
    <object>
        <name>插头电线</name>
        <pose>Unspecified</pose>
        <truncated>0</truncated>
        <difficult>0</difficult>
        <occluded>0</occluded>
        <polygon>
            <x1>43</x1>
            <y1>91</y1>
            <x2>79</x2>
            <y2>267</y2>
            <x3>91</x3>
            <y3>305</y3>
            <x4>112</x4>
            <y4>319</y4>
            <x5>122</x5>
            <y5>332</y5>
            <x6>176</x6>
            <y6>332</y6>
            <x7>176</x7>
            <y7>303</y7>
            <x8>213</x8>
            <y8>313</y8>
            <x9>178</x9>
            <y9>250</y9>
            <x10>170</x10>
            <y10>167</y10>
            <x11>212</x11>
            <y11>152</y11>
            <x12>239</x12>
            <y12>146</y12>
            <x13>242</x13>
            <y13>74</y13>
            <x14>236</x14>
            <y14>14</y14>
            <x15>188</x15>
            <y15>5</y15>
            <x16>186</x16>
            <y16>107</y16>
            <x17>164</x17>
            <y17>72</y17>
            <x18>82</x18>
            <y18>78</y18>
            <x19>52</x19>
            <y19>78</y19>
            <x20>43</x20>
            <y20>91</y20>
        </polygon>
    </object>
</annotation>
