<?xml version="1.0" encoding="UTF-8" standalone="no"?>
<annotation>
    <folder>Images</folder>
    <filename>img_18185.jpg</filename>
    <source>
        <database>Unknown</database>
    </source>
    <size>
        <width>768</width>
        <height>1024</height>
        <depth>3</depth>
    </size>
    <segmented>0</segmented>
    <object>
        <name>饮料瓶</name>
        <pose>Unspecified</pose>
        <truncated>0</truncated>
        <difficult>0</difficult>
        <occluded>0</occluded>
        <polygon>
            <x1>319</x1>
            <y1>59</y1>
            <x2>209</x2>
            <y2>622</y2>
            <x3>375</x3>
            <y3>674</y3>
            <x4>538</x4>
            <y4>91</y4>
            <x5>319</x5>
            <y5>59</y5>
        </polygon>
    </object>
    <object>
        <name>饮料瓶</name>
        <pose>Unspecified</pose>
        <truncated>0</truncated>
        <difficult>0</difficult>
        <occluded>0</occluded>
        <polygon>
            <x1>468</x1>
            <y1>636</y1>
            <x2>560</x2>
            <y2>568</y2>
            <x3>748</x3>
            <y3>716</y3>
            <x4>756</x4>
            <y4>800</y4>
            <x5>692</x5>
            <y5>806</y5>
            <x6>616</x6>
            <y6>802</y6>
            <x7>570</x7>
            <y7>742</y7>
            <x8>502</x8>
            <y8>800</y8>
            <x9>462</x9>
            <y9>826</y9>
            <x10>371</x10>
            <y10>790</y10>
            <x11>341</x11>
            <y11>742</y11>
            <x12>371</x12>
            <y12>644</y12>
            <x13>392</x13>
            <y13>590</y13>
            <x14>468</x14>
            <y14>636</y14>
        </polygon>
    </object>
</annotation>
