<?xml version="1.0" encoding="UTF-8" standalone="no"?>
<annotation>
    <folder>Images</folder>
    <filename>img_10076.jpg</filename>
    <source>
        <database>Unknown</database>
    </source>
    <size>
        <width>494</width>
        <height>345</height>
        <depth>3</depth>
    </size>
    <segmented>0</segmented>
    <object>
        <name>插头电线</name>
        <pose>Unspecified</pose>
        <truncated>0</truncated>
        <difficult>0</difficult>
        <occluded>0</occluded>
        <polygon>
            <x1>77</x1>
            <y1>44</y1>
            <x2>64</x2>
            <y2>57</y2>
            <x3>48</x3>
            <y3>61</y3>
            <x4>30</x4>
            <y4>78</y4>
            <x5>28</x5>
            <y5>116</y5>
            <x6>28</x6>
            <y6>136</y6>
            <x7>7</x7>
            <y7>145</y7>
            <x8>12</x8>
            <y8>167</y8>
            <x9>28</x9>
            <y9>170</y9>
            <x10>40</x10>
            <y10>193</y10>
            <x11>45</x11>
            <y11>256</y11>
            <x12>96</x12>
            <y12>304</y12>
            <x13>147</x13>
            <y13>332</y13>
            <x14>193</x14>
            <y14>341</y14>
            <x15>223</x15>
            <y15>341</y15>
            <x16>275</x16>
            <y16>341</y16>
            <x17>318</x17>
            <y17>337</y17>
            <x18>366</x18>
            <y18>325</y18>
            <x19>396</x19>
            <y19>306</y19>
            <x20>423</x20>
            <y20>273</y20>
            <x21>439</x21>
            <y21>256</y21>
            <x22>448</x22>
            <y22>231</y22>
            <x23>445</x23>
            <y23>207</y23>
            <x24>441</x24>
            <y24>186</y24>
            <x25>447</x25>
            <y25>161</y25>
            <x26>445</x26>
            <y26>138</y26>
            <x27>442</x27>
            <y27>110</y27>
            <x28>432</x28>
            <y28>96</y28>
            <x29>408</x29>
            <y29>71</y29>
            <x30>382</x30>
            <y30>56</y30>
            <x31>353</x31>
            <y31>42</y31>
            <x32>316</x32>
            <y32>26</y32>
            <x33>284</x33>
            <y33>26</y33>
            <x34>242</x34>
            <y34>21</y34>
            <x35>215</x35>
            <y35>21</y35>
            <x36>177</x36>
            <y36>21</y36>
            <x37>151</x37>
            <y37>24</y37>
            <x38>128</x38>
            <y38>28</y38>
            <x39>94</x39>
            <y39>33</y39>
            <x40>77</x40>
            <y40>44</y40>
        </polygon>
    </object>
</annotation>
