<?xml version="1.0" encoding="UTF-8" standalone="no"?>
<annotation>
    <folder>Images</folder>
    <filename>img_16494.jpg</filename>
    <source>
        <database>Unknown</database>
    </source>
    <size>
        <width>243</width>
        <height>455</height>
        <depth>3</depth>
    </size>
    <segmented>0</segmented>
    <object>
        <name>金属食品罐</name>
        <pose>Unspecified</pose>
        <truncated>0</truncated>
        <difficult>0</difficult>
        <occluded>0</occluded>
        <polygon>
            <x1>63</x1>
            <y1>28</y1>
            <x2>47</x2>
            <y2>39</y2>
            <x3>42</x3>
            <y3>85</y3>
            <x4>48</x4>
            <y4>119</y4>
            <x5>11</x5>
            <y5>260</y5>
            <x6>11</x6>
            <y6>299</y6>
            <x7>19</x7>
            <y7>326</y7>
            <x8>37</x8>
            <y8>344</y8>
            <x9>57</x9>
            <y9>362</y9>
            <x10>70</x10>
            <y10>373</y10>
            <x11>119</x11>
            <y11>383</y11>
            <x12>148</x12>
            <y12>373</y12>
            <x13>174</x13>
            <y13>352</y13>
            <x14>186</x14>
            <y14>322</y14>
            <x15>209</x15>
            <y15>278</y15>
            <x16>220</x16>
            <y16>208</y16>
            <x17>222</x17>
            <y17>160</y17>
            <x18>219</x18>
            <y18>88</y18>
            <x19>212</x19>
            <y19>74</y19>
            <x20>204</x20>
            <y20>37</y20>
            <x21>63</x21>
            <y21>28</y21>
        </polygon>
    </object>
</annotation>
