<?xml version="1.0" encoding="UTF-8" standalone="no"?>
<annotation>
    <folder>Images</folder>
    <filename>img_7217.jpg</filename>
    <source>
        <database>Unknown</database>
    </source>
    <size>
        <width>768</width>
        <height>1024</height>
        <depth>3</depth>
    </size>
    <segmented>0</segmented>
    <object>
        <name>包</name>
        <pose>Unspecified</pose>
        <truncated>0</truncated>
        <difficult>0</difficult>
        <occluded>0</occluded>
        <polygon>
            <x1>21</x1>
            <y1>227</y1>
            <x2>86</x2>
            <y2>305</y2>
            <x3>86</x3>
            <y3>328</y3>
            <x4>101</x4>
            <y4>375</y4>
            <x5>151</x5>
            <y5>428</y5>
            <x6>125</x6>
            <y6>464</y6>
            <x7>94</x7>
            <y7>456</y7>
            <x8>55</x8>
            <y8>451</y8>
            <x9>5</x9>
            <y9>473</y9>
            <x10>5</x10>
            <y10>589</y10>
            <x11>28</x11>
            <y11>610</y11>
            <x12>83</x12>
            <y12>611</y12>
            <x13>199</x13>
            <y13>530</y13>
            <x14>227</x14>
            <y14>540</y14>
            <x15>250</x15>
            <y15>589</y15>
            <x16>556</x16>
            <y16>749</y16>
            <x17>632</x17>
            <y17>744</y17>
            <x18>739</x18>
            <y18>634</y18>
            <x19>739</x19>
            <y19>593</y19>
            <x20>697</x20>
            <y20>525</y20>
            <x21>741</x21>
            <y21>542</y21>
            <x22>744</x22>
            <y22>577</y22>
            <x23>762</x23>
            <y23>580</y23>
            <x24>742</x24>
            <y24>204</y24>
            <x25>738</x25>
            <y25>172</y25>
            <x26>624</x26>
            <y26>138</y26>
            <x27>626</x27>
            <y27>89</y27>
            <x28>595</x28>
            <y28>84</y28>
            <x29>558</x29>
            <y29>26</y29>
            <x30>532</x30>
            <y30>57</y30>
            <x31>551</x31>
            <y31>84</y31>
            <x32>478</x32>
            <y32>122</y32>
            <x33>407</x33>
            <y33>120</y33>
            <x34>331</x34>
            <y34>117</y34>
            <x35>305</x35>
            <y35>117</y35>
            <x36>250</x36>
            <y36>107</y36>
            <x37>199</x37>
            <y37>78</y37>
            <x38>135</x38>
            <y38>65</y38>
            <x39>114</x39>
            <y39>91</y39>
            <x40>101</x40>
            <y40>130</y40>
            <x41>102</x41>
            <y41>182</y41>
            <x42>21</x42>
            <y42>227</y42>
        </polygon>
    </object>
    <object>
        <name>饮料瓶</name>
        <pose>Unspecified</pose>
        <truncated>0</truncated>
        <difficult>0</difficult>
        <occluded>0</occluded>
        <polygon>
            <x1>684</x1>
            <y1>2</y1>
            <x2>665</x2>
            <y2>141</y2>
            <x3>574</x3>
            <y3>128</y3>
            <x4>580</x4>
            <y4>5</y4>
            <x5>684</x5>
            <y5>2</y5>
        </polygon>
    </object>
</annotation>
