<?xml version="1.0" encoding="UTF-8" standalone="no"?>
<annotation>
    <folder>Images</folder>
    <filename>img_3436.jpg</filename>
    <source>
        <database>Unknown</database>
    </source>
    <size>
        <width>300</width>
        <height>240</height>
        <depth>3</depth>
    </size>
    <segmented>0</segmented>
    <object>
        <name>水果果皮</name>
        <pose>Unspecified</pose>
        <truncated>0</truncated>
        <difficult>0</difficult>
        <occluded>0</occluded>
        <polygon>
            <x1>76</x1>
            <y1>19</y1>
            <x2>61</x2>
            <y2>18</y2>
            <x3>49</x3>
            <y3>24</y3>
            <x4>25</x4>
            <y4>55</y4>
            <x5>5</x5>
            <y5>65</y5>
            <x6>3</x6>
            <y6>183</y6>
            <x7>21</x7>
            <y7>191</y7>
            <x8>20</x8>
            <y8>208</y8>
            <x9>29</x9>
            <y9>232</y9>
            <x10>38</x10>
            <y10>218</y10>
            <x11>41</x11>
            <y11>237</y11>
            <x12>55</x12>
            <y12>218</y12>
            <x13>63</x13>
            <y13>202</y13>
            <x14>80</x14>
            <y14>207</y14>
            <x15>100</x15>
            <y15>182</y15>
            <x16>103</x16>
            <y16>201</y16>
            <x17>114</x17>
            <y17>212</y17>
            <x18>128</x18>
            <y18>215</y18>
            <x19>153</x19>
            <y19>236</y19>
            <x20>236</x20>
            <y20>237</y20>
            <x21>235</x21>
            <y21>211</y21>
            <x22>229</x22>
            <y22>186</y22>
            <x23>216</x23>
            <y23>174</y23>
            <x24>220</x24>
            <y24>173</y24>
            <x25>228</x25>
            <y25>173</y25>
            <x26>233</x26>
            <y26>177</y26>
            <x27>236</x27>
            <y27>191</y27>
            <x28>235</x28>
            <y28>198</y28>
            <x29>245</x29>
            <y29>201</y29>
            <x30>244</x30>
            <y30>217</y30>
            <x31>239</x31>
            <y31>223</y31>
            <x32>249</x32>
            <y32>225</y32>
            <x33>261</x33>
            <y33>210</y33>
            <x34>266</x34>
            <y34>195</y34>
            <x35>267</x35>
            <y35>180</y35>
            <x36>274</x36>
            <y36>165</y36>
            <x37>278</x37>
            <y37>149</y37>
            <x38>272</x38>
            <y38>135</y38>
            <x39>260</x39>
            <y39>130</y39>
            <x40>248</x40>
            <y40>124</y40>
            <x41>272</x41>
            <y41>124</y41>
            <x42>280</x42>
            <y42>112</y42>
            <x43>297</x43>
            <y43>101</y43>
            <x44>298</x44>
            <y44>88</y44>
            <x45>299</x45>
            <y45>73</y45>
            <x46>248</x46>
            <y46>33</y46>
            <x47>214</x47>
            <y47>32</y47>
            <x48>200</x48>
            <y48>41</y48>
            <x49>190</x49>
            <y49>30</y49>
            <x50>160</x50>
            <y50>2</y50>
            <x51>79</x51>
            <y51>2</y51>
            <x52>74</x52>
            <y52>14</y52>
            <x53>76</x53>
            <y53>19</y53>
        </polygon>
    </object>
</annotation>
