<?xml version="1.0" encoding="UTF-8" standalone="no"?>
<annotation>
    <folder>Images</folder>
    <filename>img_2053.jpg</filename>
    <source>
        <database>Unknown</database>
    </source>
    <size>
        <width>768</width>
        <height>1024</height>
        <depth>3</depth>
    </size>
    <segmented>0</segmented>
    <object>
        <name>竹筷</name>
        <pose>Unspecified</pose>
        <truncated>0</truncated>
        <difficult>0</difficult>
        <occluded>0</occluded>
        <polygon>
            <x1>7</x1>
            <y1>708</y1>
            <x2>538</x2>
            <y2>299</y2>
            <x3>634</x3>
            <y3>359</y3>
            <x4>5</x4>
            <y4>868</y4>
            <x5>7</x5>
            <y5>708</y5>
        </polygon>
    </object>
</annotation>
