<?xml version="1.0" encoding="UTF-8" standalone="no"?>
<annotation>
    <folder>Images</folder>
    <filename>img_8962.jpg</filename>
    <source>
        <database>Unknown</database>
    </source>
    <size>
        <width>225</width>
        <height>400</height>
        <depth>3</depth>
    </size>
    <segmented>0</segmented>
    <object>
        <name>塑料碗盆</name>
        <pose>Unspecified</pose>
        <truncated>0</truncated>
        <difficult>0</difficult>
        <occluded>0</occluded>
        <polygon>
            <x1>1</x1>
            <y1>130</y1>
            <x2>11</x2>
            <y2>118</y2>
            <x3>44</x3>
            <y3>108</y3>
            <x4>66</x4>
            <y4>102</y4>
            <x5>109</x5>
            <y5>97</y5>
            <x6>133</x6>
            <y6>97</y6>
            <x7>161</x7>
            <y7>102</y7>
            <x8>189</x8>
            <y8>119</y8>
            <x9>220</x9>
            <y9>143</y9>
            <x10>224</x10>
            <y10>242</y10>
            <x11>214</x11>
            <y11>259</y11>
            <x12>196</x12>
            <y12>276</y12>
            <x13>170</x13>
            <y13>290</y13>
            <x14>143</x14>
            <y14>299</y14>
            <x15>111</x15>
            <y15>305</y15>
            <x16>71</x16>
            <y16>308</y16>
            <x17>27</x17>
            <y17>297</y17>
            <x18>9</x18>
            <y18>281</y18>
            <x19>0</x19>
            <y19>265</y19>
            <x20>1</x20>
            <y20>130</y20>
        </polygon>
    </object>
</annotation>
